lifeguard_notification_msteams/__init__.py
lifeguard_notification_msteams/notifications.py
lifeguard_notification_msteams/settings.py
lifeguard_notification_msteams-0.0.4.dist-info/METADATA
lifeguard_notification_msteams-0.0.4.dist-info/WHEEL
lifeguard_notification_msteams-0.0.4.dist-info/top_level.txt
lifeguard_notification_msteams-0.0.4.dist-info/RECORD
