Metadata-Version: 2.1
Name: lifeguard-notification-msteams
Version: 0.0.4
Summary: Lifeguard integration with MS Teams
Home-page: https://github.com/LifeguardSystem/lifeguard-notification-msteams
Author: Diego Rubin
Author-email: contact@diegorubin.dev
License: GPL2
Classifier: Development Status :: 5 - Production/Stable
Classifier: Intended Audience :: Developers
Classifier: Intended Audience :: Information Technology
Classifier: Programming Language :: Python
Classifier: Programming Language :: Python :: 3
Classifier: Topic :: System :: Monitoring
Requires-Dist: lifeguard
Requires-Dist: pymsteams
